{
  "ID": "f90e8fba-6bf2-489f-a9c5-2fcb243f9504",
  "Version": "2.3.3.0",
  "Name": "newFennuyouhun",
  "Content": {
    "Content": {
      "Animation": {
        "Duration": 260,
        "Speed": 1.0,
        "Timelines": [
          {
            "ActionTag": 1459686813,
            "Property": "Scale",
            "Frames": [
              {
                "X": 1.0,
                "Y": 1.0,
                "FrameIndex": 171,
                "EasingData": {
                  "Type": 0
                },
                "ctype": "ScaleValueFrameData"
              }
            ],
            "ctype": "TimelineData"
          },
          {
            "ActionTag": 1459686813,
            "Property": "Alpha",
            "Frames": [
              {
                "Value": 255,
                "FrameIndex": 171,
                "EasingData": {
                  "Type": 0
                },
                "ctype": "IntFrameData"
              },
              {
                "Value": 255,
                "FrameIndex": 190,
                "EasingData": {
                  "Type": 0
                },
                "ctype": "IntFrameData"
              },
              {
                "Value": 0,
                "FrameIndex": 260,
                "EasingData": {
                  "Type": 0
                },
                "ctype": "IntFrameData"
              }
            ],
            "ctype": "TimelineData"
          },
          {
            "ActionTag": -46686393,
            "Property": "Position",
            "Frames": [
              {
                "X": 20.2947,
                "Y": 316.7978,
                "FrameIndex": 0,
                "EasingData": {
                  "Type": 0
                },
                "ctype": "PointFrameData"
              },
              {
                "X": 20.2947,
                "Y": 329.7976,
                "FrameIndex": 60,
                "EasingData": {
                  "Type": 0
                },
                "ctype": "PointFrameData"
              },
              {
                "X": 20.2947,
                "Y": 316.7978,
                "FrameIndex": 120,
                "EasingData": {
                  "Type": 0
                },
                "ctype": "PointFrameData"
              },
              {
                "X": 20.2947,
                "Y": 316.7978,
                "FrameIndex": 121,
                "EasingData": {
                  "Type": 0
                },
                "ctype": "PointFrameData"
              },
              {
                "X": 20.2941,
                "Y": 332.8,
                "FrameIndex": 130,
                "EasingData": {
                  "Type": 0
                },
                "ctype": "PointFrameData"
              },
              {
                "X": 40.0308,
                "Y": 308.3367,
                "FrameIndex": 135,
                "EasingData": {
                  "Type": 0
                },
                "ctype": "PointFrameData"
              },
              {
                "X": 26.636,
                "Y": 317.22,
                "FrameIndex": 140,
                "EasingData": {
                  "Type": 0
                },
                "ctype": "PointFrameData"
              },
              {
                "X": 20.2947,
                "Y": 316.7978,
                "FrameIndex": 150,
                "EasingData": {
                  "Type": 0
                },
                "ctype": "PointFrameData"
              },
              {
                "X": 20.2947,
                "Y": 316.7978,
                "FrameIndex": 151,
                "EasingData": {
                  "Type": 0
                },
                "ctype": "PointFrameData"
              },
              {
                "X": 30.2949,
                "Y": 316.7978,
                "FrameIndex": 155,
                "EasingData": {
                  "Type": 0
                },
                "ctype": "PointFrameData"
              },
              {
                "X": 8.2949,
                "Y": 316.7978,
                "FrameIndex": 160,
                "EasingData": {
                  "Type": 0
                },
                "ctype": "PointFrameData"
              },
              {
                "X": 20.2947,
                "Y": 306.7978,
                "FrameIndex": 165,
                "EasingData": {
                  "Type": 0
                },
                "ctype": "PointFrameData"
              },
              {
                "X": 20.2947,
                "Y": 316.7978,
                "FrameIndex": 170,
                "EasingData": {
                  "Type": 0
                },
                "ctype": "PointFrameData"
              },
              {
                "X": 20.2947,
                "Y": 316.7978,
                "FrameIndex": 171,
                "EasingData": {
                  "Type": 0
                },
                "ctype": "PointFrameData"
              },
              {
                "X": 20.2947,
                "Y": 316.7978,
                "FrameIndex": 190,
                "EasingData": {
                  "Type": 0
                },
                "ctype": "PointFrameData"
              },
              {
                "X": 20.2947,
                "Y": 316.7978,
                "FrameIndex": 260,
                "EasingData": {
                  "Type": 0
                },
                "ctype": "PointFrameData"
              }
            ],
            "ctype": "TimelineData"
          },
          {
            "ActionTag": -46686393,
            "Property": "Scale",
            "Frames": [
              {
                "X": 1.0,
                "Y": 1.0,
                "FrameIndex": 0,
                "EasingData": {
                  "Type": 0
                },
                "ctype": "ScaleValueFrameData"
              },
              {
                "X": 1.0,
                "Y": 1.02,
                "FrameIndex": 60,
                "EasingData": {
                  "Type": 0
                },
                "ctype": "ScaleValueFrameData"
              },
              {
                "X": 1.0,
                "Y": 1.0,
                "FrameIndex": 120,
                "EasingData": {
                  "Type": 0
                },
                "ctype": "ScaleValueFrameData"
              },
              {
                "X": 1.0,
                "Y": 1.0,
                "FrameIndex": 121,
                "EasingData": {
                  "Type": 0
                },
                "ctype": "ScaleValueFrameData"
              },
              {
                "X": 1.0,
                "Y": 1.02,
                "FrameIndex": 130,
                "EasingData": {
                  "Type": 0
                },
                "ctype": "ScaleValueFrameData"
              },
              {
                "X": 1.0,
                "Y": 1.0,
                "FrameIndex": 150,
                "EasingData": {
                  "Type": 0
                },
                "ctype": "ScaleValueFrameData"
              },
              {
                "X": 1.0,
                "Y": 1.0,
                "FrameIndex": 151,
                "EasingData": {
                  "Type": 0
                },
                "ctype": "ScaleValueFrameData"
              },
              {
                "X": 1.0,
                "Y": 1.0,
                "FrameIndex": 155,
                "EasingData": {
                  "Type": 0
                },
                "ctype": "ScaleValueFrameData"
              },
              {
                "X": 1.0,
                "Y": 1.0,
                "FrameIndex": 160,
                "EasingData": {
                  "Type": 0
                },
                "ctype": "ScaleValueFrameData"
              },
              {
                "X": 1.0,
                "Y": 1.0,
                "FrameIndex": 165,
                "EasingData": {
                  "Type": 0
                },
                "ctype": "ScaleValueFrameData"
              },
              {
                "X": 1.0,
                "Y": 1.0,
                "FrameIndex": 170,
                "EasingData": {
                  "Type": 0
                },
                "ctype": "ScaleValueFrameData"
              },
              {
                "X": 1.0,
                "Y": 1.0,
                "FrameIndex": 171,
                "EasingData": {
                  "Type": 0
                },
                "ctype": "ScaleValueFrameData"
              },
              {
                "X": 1.0,
                "Y": 1.0,
                "FrameIndex": 190,
                "EasingData": {
                  "Type": 0
                },
                "ctype": "ScaleValueFrameData"
              },
              {
                "X": 1.0,
                "Y": 1.0,
                "FrameIndex": 260,
                "EasingData": {
                  "Type": 0
                },
                "ctype": "ScaleValueFrameData"
              }
            ],
            "ctype": "TimelineData"
          },
          {
            "ActionTag": -46686393,
            "Property": "RotationSkew",
            "Frames": [
              {
                "X": 0.0,
                "Y": 0.0,
                "FrameIndex": 0,
                "EasingData": {
                  "Type": 0
                },
                "ctype": "ScaleValueFrameData"
              },
              {
                "X": 0.0,
                "Y": 0.0,
                "FrameIndex": 60,
                "EasingData": {
                  "Type": 0
                },
                "ctype": "ScaleValueFrameData"
              },
              {
                "X": 0.0,
                "Y": 0.0,
                "FrameIndex": 120,
                "EasingData": {
                  "Type": 0
                },
                "ctype": "ScaleValueFrameData"
              },
              {
                "X": 0.0,
                "Y": 0.0,
                "FrameIndex": 121,
                "EasingData": {
                  "Type": 0
                },
                "ctype": "ScaleValueFrameData"
              },
              {
                "X": -24.83,
                "Y": -24.8335,
                "FrameIndex": 130,
                "EasingData": {
                  "Type": 0
                },
                "ctype": "ScaleValueFrameData"
              },
              {
                "X": 54.3893,
                "Y": 54.3891,
                "FrameIndex": 135,
                "EasingData": {
                  "Type": 0
                },
                "ctype": "ScaleValueFrameData"
              },
              {
                "X": -5.7922,
                "Y": -5.7887,
                "FrameIndex": 140,
                "EasingData": {
                  "Type": 0
                },
                "ctype": "ScaleValueFrameData"
              },
              {
                "X": 0.0,
                "Y": 0.0,
                "FrameIndex": 150,
                "EasingData": {
                  "Type": 0
                },
                "ctype": "ScaleValueFrameData"
              },
              {
                "X": 0.0,
                "Y": 0.0,
                "FrameIndex": 151,
                "EasingData": {
                  "Type": 0
                },
                "ctype": "ScaleValueFrameData"
              },
              {
                "X": 0.0,
                "Y": 0.0,
                "FrameIndex": 155,
                "EasingData": {
                  "Type": 0
                },
                "ctype": "ScaleValueFrameData"
              },
              {
                "X": 0.0,
                "Y": 0.0,
                "FrameIndex": 160,
                "EasingData": {
                  "Type": 0
                },
                "ctype": "ScaleValueFrameData"
              },
              {
                "X": 0.0,
                "Y": 0.0,
                "FrameIndex": 165,
                "EasingData": {
                  "Type": 0
                },
                "ctype": "ScaleValueFrameData"
              },
              {
                "X": 0.0,
                "Y": 0.0,
                "FrameIndex": 170,
                "EasingData": {
                  "Type": 0
                },
                "ctype": "ScaleValueFrameData"
              },
              {
                "X": 0.0,
                "Y": 0.0,
                "FrameIndex": 171,
                "EasingData": {
                  "Type": 0
                },
                "ctype": "ScaleValueFrameData"
              },
              {
                "X": 0.0,
                "Y": 0.0,
                "FrameIndex": 190,
                "EasingData": {
                  "Type": 0
                },
                "ctype": "ScaleValueFrameData"
              },
              {
                "X": 0.0,
                "Y": 0.0,
                "FrameIndex": 260,
                "EasingData": {
                  "Type": 0
                },
                "ctype": "ScaleValueFrameData"
              }
            ],
            "ctype": "TimelineData"
          },
          {
            "ActionTag": -46686393,
            "Property": "Alpha",
            "Frames": [
              {
                "Value": 255,
                "FrameIndex": 190,
                "EasingData": {
                  "Type": 0
                },
                "ctype": "IntFrameData"
              },
              {
                "Value": 0,
                "FrameIndex": 260,
                "EasingData": {
                  "Type": 0
                },
                "ctype": "IntFrameData"
              }
            ],
            "ctype": "TimelineData"
          },
          {
            "ActionTag": -46686393,
            "Property": "CColor",
            "Frames": [
              {
                "Alpha": 255,
                "Color": {},
                "FrameIndex": 151,
                "EasingData": {
                  "Type": 0
                },
                "ctype": "ColorFrameData"
              },
              {
                "Alpha": 255,
                "Color": {
                  "G": 0,
                  "B": 0
                },
                "FrameIndex": 155,
                "EasingData": {
                  "Type": 0
                },
                "ctype": "ColorFrameData"
              },
              {
                "Alpha": 255,
                "Color": {},
                "FrameIndex": 160,
                "EasingData": {
                  "Type": 0
                },
                "ctype": "ColorFrameData"
              },
              {
                "Alpha": 255,
                "Color": {
                  "G": 0,
                  "B": 0
                },
                "FrameIndex": 165,
                "EasingData": {
                  "Type": 0
                },
                "ctype": "ColorFrameData"
              },
              {
                "Alpha": 255,
                "Color": {},
                "FrameIndex": 170,
                "EasingData": {
                  "Type": 0
                },
                "ctype": "ColorFrameData"
              }
            ],
            "ctype": "TimelineData"
          },
          {
            "ActionTag": -1583887602,
            "Property": "Position",
            "Frames": [
              {
                "X": 8.8333,
                "Y": 217.5331,
                "FrameIndex": 0,
                "EasingData": {
                  "Type": 0
                },
                "ctype": "PointFrameData"
              },
              {
                "X": 8.8335,
                "Y": 230.533,
                "FrameIndex": 60,
                "EasingData": {
                  "Type": 0
                },
                "ctype": "PointFrameData"
              },
              {
                "X": 8.8333,
                "Y": 217.5331,
                "FrameIndex": 120,
                "EasingData": {
                  "Type": 0
                },
                "ctype": "PointFrameData"
              },
              {
                "X": 8.8333,
                "Y": 217.5331,
                "FrameIndex": 121,
                "EasingData": {
                  "Type": 0
                },
                "ctype": "PointFrameData"
              },
              {
                "X": 8.8333,
                "Y": 229.53,
                "FrameIndex": 130,
                "EasingData": {
                  "Type": 0
                },
                "ctype": "PointFrameData"
              },
              {
                "X": 8.8333,
                "Y": 222.53,
                "FrameIndex": 135,
                "EasingData": {
                  "Type": 0
                },
                "ctype": "PointFrameData"
              },
              {
                "X": 8.8333,
                "Y": 217.5331,
                "FrameIndex": 150,
                "EasingData": {
                  "Type": 0
                },
                "ctype": "PointFrameData"
              },
              {
                "X": 8.8333,
                "Y": 217.5331,
                "FrameIndex": 151,
                "EasingData": {
                  "Type": 0
                },
                "ctype": "PointFrameData"
              },
              {
                "X": 18.8336,
                "Y": 217.5331,
                "FrameIndex": 155,
                "EasingData": {
                  "Type": 0
                },
                "ctype": "PointFrameData"
              },
              {
                "X": -3.1664,
                "Y": 217.5331,
                "FrameIndex": 160,
                "EasingData": {
                  "Type": 0
                },
                "ctype": "PointFrameData"
              },
              {
                "X": 8.8334,
                "Y": 207.5331,
                "FrameIndex": 165,
                "EasingData": {
                  "Type": 0
                },
                "ctype": "PointFrameData"
              },
              {
                "X": 8.8333,
                "Y": 217.5331,
                "FrameIndex": 170,
                "EasingData": {
                  "Type": 0
                },
                "ctype": "PointFrameData"
              },
              {
                "X": 8.8333,
                "Y": 217.5331,
                "FrameIndex": 171,
                "EasingData": {
                  "Type": 0
                },
                "ctype": "PointFrameData"
              },
              {
                "X": 8.8333,
                "Y": 217.5331,
                "FrameIndex": 190,
                "EasingData": {
                  "Type": 0
                },
                "ctype": "PointFrameData"
              },
              {
                "X": 8.8333,
                "Y": 217.5331,
                "FrameIndex": 260,
                "EasingData": {
                  "Type": 0
                },
                "ctype": "PointFrameData"
              }
            ],
            "ctype": "TimelineData"
          },
          {
            "ActionTag": -1583887602,
            "Property": "Scale",
            "Frames": [
              {
                "X": 1.0,
                "Y": 1.0,
                "FrameIndex": 0,
                "EasingData": {
                  "Type": 0
                },
                "ctype": "ScaleValueFrameData"
              },
              {
                "X": 1.0,
                "Y": 1.02,
                "FrameIndex": 60,
                "EasingData": {
                  "Type": 0
                },
                "ctype": "ScaleValueFrameData"
              },
              {
                "X": 1.0,
                "Y": 1.0,
                "FrameIndex": 120,
                "EasingData": {
                  "Type": 0
                },
                "ctype": "ScaleValueFrameData"
              },
              {
                "X": 1.0,
                "Y": 1.0,
                "FrameIndex": 121,
                "EasingData": {
                  "Type": 0
                },
                "ctype": "ScaleValueFrameData"
              },
              {
                "X": 1.0,
                "Y": 1.02,
                "FrameIndex": 130,
                "EasingData": {
                  "Type": 0
                },
                "ctype": "ScaleValueFrameData"
              },
              {
                "X": 1.0,
                "Y": 0.995,
                "FrameIndex": 135,
                "EasingData": {
                  "Type": 0
                },
                "ctype": "ScaleValueFrameData"
              },
              {
                "X": 1.0,
                "Y": 1.0,
                "FrameIndex": 150,
                "EasingData": {
                  "Type": 0
                },
                "ctype": "ScaleValueFrameData"
              },
              {
                "X": 1.0,
                "Y": 1.0,
                "FrameIndex": 151,
                "EasingData": {
                  "Type": 0
                },
                "ctype": "ScaleValueFrameData"
              },
              {
                "X": 1.0,
                "Y": 1.0,
                "FrameIndex": 155,
                "EasingData": {
                  "Type": 0
                },
                "ctype": "ScaleValueFrameData"
              },
              {
                "X": 1.0,
                "Y": 1.0,
                "FrameIndex": 160,
                "EasingData": {
                  "Type": 0
                },
                "ctype": "ScaleValueFrameData"
              },
              {
                "X": 1.0,
                "Y": 1.0,
                "FrameIndex": 165,
                "EasingData": {
                  "Type": 0
                },
                "ctype": "ScaleValueFrameData"
              },
              {
                "X": 1.0,
                "Y": 1.0,
                "FrameIndex": 170,
                "EasingData": {
                  "Type": 0
                },
                "ctype": "ScaleValueFrameData"
              },
              {
                "X": 1.0,
                "Y": 1.0,
                "FrameIndex": 171,
                "EasingData": {
                  "Type": 0
                },
                "ctype": "ScaleValueFrameData"
              },
              {
                "X": 1.0,
                "Y": 1.0,
                "FrameIndex": 190,
                "EasingData": {
                  "Type": 0
                },
                "ctype": "ScaleValueFrameData"
              },
              {
                "X": 1.0,
                "Y": 1.0,
                "FrameIndex": 260,
                "EasingData": {
                  "Type": 0
                },
                "ctype": "ScaleValueFrameData"
              }
            ],
            "ctype": "TimelineData"
          },
          {
            "ActionTag": -1583887602,
            "Property": "RotationSkew",
            "Frames": [
              {
                "X": 0.0,
                "Y": 0.0,
                "FrameIndex": 0,
                "EasingData": {
                  "Type": 0
                },
                "ctype": "ScaleValueFrameData"
              },
              {
                "X": 0.0,
                "Y": 0.0,
                "FrameIndex": 60,
                "EasingData": {
                  "Type": 0
                },
                "ctype": "ScaleValueFrameData"
              },
              {
                "X": 0.0,
                "Y": 0.0,
                "FrameIndex": 120,
                "EasingData": {
                  "Type": 0
                },
                "ctype": "ScaleValueFrameData"
              },
              {
                "X": 0.0,
                "Y": 0.0,
                "FrameIndex": 121,
                "EasingData": {
                  "Type": 0
                },
                "ctype": "ScaleValueFrameData"
              },
              {
                "X": 0.0,
                "Y": 0.0,
                "FrameIndex": 150,
                "EasingData": {
                  "Type": 0
                },
                "ctype": "ScaleValueFrameData"
              },
              {
                "X": 0.0,
                "Y": 0.0,
                "FrameIndex": 151,
                "EasingData": {
                  "Type": 0
                },
                "ctype": "ScaleValueFrameData"
              },
              {
                "X": 0.0,
                "Y": 0.0,
                "FrameIndex": 155,
                "EasingData": {
                  "Type": 0
                },
                "ctype": "ScaleValueFrameData"
              },
              {
                "X": 0.0,
                "Y": 0.0,
                "FrameIndex": 160,
                "EasingData": {
                  "Type": 0
                },
                "ctype": "ScaleValueFrameData"
              },
              {
                "X": 0.0,
                "Y": 0.0,
                "FrameIndex": 165,
                "EasingData": {
                  "Type": 0
                },
                "ctype": "ScaleValueFrameData"
              },
              {
                "X": 0.0,
                "Y": 0.0,
                "FrameIndex": 170,
                "EasingData": {
                  "Type": 0
                },
                "ctype": "ScaleValueFrameData"
              },
              {
                "X": 0.0,
                "Y": 0.0,
                "FrameIndex": 171,
                "EasingData": {
                  "Type": 0
                },
                "ctype": "ScaleValueFrameData"
              },
              {
                "X": 0.0,
                "Y": 0.0,
                "FrameIndex": 190,
                "EasingData": {
                  "Type": 0
                },
                "ctype": "ScaleValueFrameData"
              },
              {
                "X": 0.0,
                "Y": 0.0,
                "FrameIndex": 260,
                "EasingData": {
                  "Type": 0
                },
                "ctype": "ScaleValueFrameData"
              }
            ],
            "ctype": "TimelineData"
          },
          {
            "ActionTag": -1583887602,
            "Property": "Alpha",
            "Frames": [
              {
                "Value": 255,
                "FrameIndex": 190,
                "EasingData": {
                  "Type": 0
                },
                "ctype": "IntFrameData"
              },
              {
                "Value": 0,
                "FrameIndex": 260,
                "EasingData": {
                  "Type": 0
                },
                "ctype": "IntFrameData"
              }
            ],
            "ctype": "TimelineData"
          },
          {
            "ActionTag": -1583887602,
            "Property": "CColor",
            "Frames": [
              {
                "Alpha": 255,
                "Color": {},
                "FrameIndex": 151,
                "EasingData": {
                  "Type": 0
                },
                "ctype": "ColorFrameData"
              },
              {
                "Alpha": 255,
                "Color": {
                  "G": 0,
                  "B": 0
                },
                "FrameIndex": 155,
                "EasingData": {
                  "Type": 0
                },
                "ctype": "ColorFrameData"
              },
              {
                "Alpha": 255,
                "Color": {},
                "FrameIndex": 160,
                "EasingData": {
                  "Type": 0
                },
                "ctype": "ColorFrameData"
              },
              {
                "Alpha": 255,
                "Color": {
                  "G": 0,
                  "B": 0
                },
                "FrameIndex": 165,
                "EasingData": {
                  "Type": 0
                },
                "ctype": "ColorFrameData"
              },
              {
                "Alpha": 255,
                "Color": {},
                "FrameIndex": 170,
                "EasingData": {
                  "Type": 0
                },
                "ctype": "ColorFrameData"
              }
            ],
            "ctype": "TimelineData"
          },
          {
            "ActionTag": -2026200248,
            "Property": "Position",
            "Frames": [
              {
                "X": 2.8178,
                "Y": 33.3434,
                "FrameIndex": 0,
                "EasingData": {
                  "Type": 0
                },
                "ctype": "PointFrameData"
              },
              {
                "X": 2.8176,
                "Y": 41.3435,
                "FrameIndex": 60,
                "EasingData": {
                  "Type": 0
                },
                "ctype": "PointFrameData"
              },
              {
                "X": 2.8178,
                "Y": 33.3434,
                "FrameIndex": 120,
                "EasingData": {
                  "Type": 0
                },
                "ctype": "PointFrameData"
              },
              {
                "X": 2.8178,
                "Y": 33.3434,
                "FrameIndex": 121,
                "EasingData": {
                  "Type": 0
                },
                "ctype": "PointFrameData"
              },
              {
                "X": 2.8178,
                "Y": 38.34,
                "FrameIndex": 130,
                "EasingData": {
                  "Type": 0
                },
                "ctype": "PointFrameData"
              },
              {
                "X": 2.8178,
                "Y": 33.3434,
                "FrameIndex": 150,
                "EasingData": {
                  "Type": 0
                },
                "ctype": "PointFrameData"
              },
              {
                "X": 2.8178,
                "Y": 33.3434,
                "FrameIndex": 151,
                "EasingData": {
                  "Type": 0
                },
                "ctype": "PointFrameData"
              },
              {
                "X": 12.818,
                "Y": 33.3434,
                "FrameIndex": 155,
                "EasingData": {
                  "Type": 0
                },
                "ctype": "PointFrameData"
              },
              {
                "X": -9.1822,
                "Y": 33.3434,
                "FrameIndex": 160,
                "EasingData": {
                  "Type": 0
                },
                "ctype": "PointFrameData"
              },
              {
                "X": 2.8176,
                "Y": 23.3434,
                "FrameIndex": 165,
                "EasingData": {
                  "Type": 0
                },
                "ctype": "PointFrameData"
              },
              {
                "X": 2.8178,
                "Y": 33.3434,
                "FrameIndex": 170,
                "EasingData": {
                  "Type": 0
                },
                "ctype": "PointFrameData"
              },
              {
                "X": 2.8178,
                "Y": 33.3434,
                "FrameIndex": 171,
                "EasingData": {
                  "Type": 0
                },
                "ctype": "PointFrameData"
              },
              {
                "X": 2.8178,
                "Y": 33.3434,
                "FrameIndex": 190,
                "EasingData": {
                  "Type": 0
                },
                "ctype": "PointFrameData"
              },
              {
                "X": 2.8178,
                "Y": 33.3434,
                "FrameIndex": 260,
                "EasingData": {
                  "Type": 0
                },
                "ctype": "PointFrameData"
              }
            ],
            "ctype": "TimelineData"
          },
          {
            "ActionTag": -2026200248,
            "Property": "Scale",
            "Frames": [
              {
                "X": 1.0,
                "Y": 1.0,
                "FrameIndex": 0,
                "EasingData": {
                  "Type": 0
                },
                "ctype": "ScaleValueFrameData"
              },
              {
                "X": 1.0,
                "Y": 1.02,
                "FrameIndex": 60,
                "EasingData": {
                  "Type": 0
                },
                "ctype": "ScaleValueFrameData"
              },
              {
                "X": 1.0,
                "Y": 1.0,
                "FrameIndex": 120,
                "EasingData": {
                  "Type": 0
                },
                "ctype": "ScaleValueFrameData"
              },
              {
                "X": 1.0,
                "Y": 1.0,
                "FrameIndex": 121,
                "EasingData": {
                  "Type": 0
                },
                "ctype": "ScaleValueFrameData"
              },
              {
                "X": 1.0,
                "Y": 1.02,
                "FrameIndex": 130,
                "EasingData": {
                  "Type": 0
                },
                "ctype": "ScaleValueFrameData"
              },
              {
                "X": 1.0,
                "Y": 0.995,
                "FrameIndex": 135,
                "EasingData": {
                  "Type": 0
                },
                "ctype": "ScaleValueFrameData"
              },
              {
                "X": 1.0,
                "Y": 1.0,
                "FrameIndex": 150,
                "EasingData": {
                  "Type": 0
                },
                "ctype": "ScaleValueFrameData"
              },
              {
                "X": 1.0,
                "Y": 1.0,
                "FrameIndex": 151,
                "EasingData": {
                  "Type": 0
                },
                "ctype": "ScaleValueFrameData"
              },
              {
                "X": 1.0,
                "Y": 1.0,
                "FrameIndex": 155,
                "EasingData": {
                  "Type": 0
                },
                "ctype": "ScaleValueFrameData"
              },
              {
                "X": 1.0,
                "Y": 1.0,
                "FrameIndex": 160,
                "EasingData": {
                  "Type": 0
                },
                "ctype": "ScaleValueFrameData"
              },
              {
                "X": 1.0,
                "Y": 1.0,
                "FrameIndex": 165,
                "EasingData": {
                  "Type": 0
                },
                "ctype": "ScaleValueFrameData"
              },
              {
                "X": 1.0,
                "Y": 1.0,
                "FrameIndex": 170,
                "EasingData": {
                  "Type": 0
                },
                "ctype": "ScaleValueFrameData"
              },
              {
                "X": 1.0,
                "Y": 1.0,
                "FrameIndex": 171,
                "EasingData": {
                  "Type": 0
                },
                "ctype": "ScaleValueFrameData"
              },
              {
                "X": 1.0,
                "Y": 1.0,
                "FrameIndex": 190,
                "EasingData": {
                  "Type": 0
                },
                "ctype": "ScaleValueFrameData"
              },
              {
                "X": 1.0,
                "Y": 1.0,
                "FrameIndex": 260,
                "EasingData": {
                  "Type": 0
                },
                "ctype": "ScaleValueFrameData"
              }
            ],
            "ctype": "TimelineData"
          },
          {
            "ActionTag": -2026200248,
            "Property": "RotationSkew",
            "Frames": [
              {
                "X": 0.0,
                "Y": 0.0,
                "FrameIndex": 0,
                "EasingData": {
                  "Type": 0
                },
                "ctype": "ScaleValueFrameData"
              },
              {
                "X": 0.0,
                "Y": 0.0,
                "FrameIndex": 60,
                "EasingData": {
                  "Type": 0
                },
                "ctype": "ScaleValueFrameData"
              },
              {
                "X": 0.0,
                "Y": 0.0,
                "FrameIndex": 120,
                "EasingData": {
                  "Type": 0
                },
                "ctype": "ScaleValueFrameData"
              },
              {
                "X": 0.0,
                "Y": 0.0,
                "FrameIndex": 121,
                "EasingData": {
                  "Type": 0
                },
                "ctype": "ScaleValueFrameData"
              },
              {
                "X": 0.0,
                "Y": 0.0,
                "FrameIndex": 150,
                "EasingData": {
                  "Type": 0
                },
                "ctype": "ScaleValueFrameData"
              },
              {
                "X": 0.0,
                "Y": 0.0,
                "FrameIndex": 151,
                "EasingData": {
                  "Type": 0
                },
                "ctype": "ScaleValueFrameData"
              },
              {
                "X": 0.0,
                "Y": 0.0,
                "FrameIndex": 155,
                "EasingData": {
                  "Type": 0
                },
                "ctype": "ScaleValueFrameData"
              },
              {
                "X": 0.0,
                "Y": 0.0,
                "FrameIndex": 160,
                "EasingData": {
                  "Type": 0
                },
                "ctype": "ScaleValueFrameData"
              },
              {
                "X": 0.0,
                "Y": 0.0,
                "FrameIndex": 165,
                "EasingData": {
                  "Type": 0
                },
                "ctype": "ScaleValueFrameData"
              },
              {
                "X": 0.0,
                "Y": 0.0,
                "FrameIndex": 170,
                "EasingData": {
                  "Type": 0
                },
                "ctype": "ScaleValueFrameData"
              },
              {
                "X": 0.0,
                "Y": 0.0,
                "FrameIndex": 171,
                "EasingData": {
                  "Type": 0
                },
                "ctype": "ScaleValueFrameData"
              },
              {
                "X": 0.0,
                "Y": 0.0,
                "FrameIndex": 190,
                "EasingData": {
                  "Type": 0
                },
                "ctype": "ScaleValueFrameData"
              },
              {
                "X": 0.0,
                "Y": 0.0,
                "FrameIndex": 260,
                "EasingData": {
                  "Type": 0
                },
                "ctype": "ScaleValueFrameData"
              }
            ],
            "ctype": "TimelineData"
          },
          {
            "ActionTag": -2026200248,
            "Property": "Alpha",
            "Frames": [
              {
                "Value": 255,
                "FrameIndex": 190,
                "EasingData": {
                  "Type": 0
                },
                "ctype": "IntFrameData"
              },
              {
                "Value": 0,
                "FrameIndex": 260,
                "EasingData": {
                  "Type": 0
                },
                "ctype": "IntFrameData"
              }
            ],
            "ctype": "TimelineData"
          },
          {
            "ActionTag": -2026200248,
            "Property": "CColor",
            "Frames": [
              {
                "Alpha": 255,
                "Color": {},
                "FrameIndex": 151,
                "EasingData": {
                  "Type": 0
                },
                "ctype": "ColorFrameData"
              },
              {
                "Alpha": 255,
                "Color": {
                  "G": 0,
                  "B": 0
                },
                "FrameIndex": 155,
                "EasingData": {
                  "Type": 0
                },
                "ctype": "ColorFrameData"
              },
              {
                "Alpha": 255,
                "Color": {},
                "FrameIndex": 160,
                "EasingData": {
                  "Type": 0
                },
                "ctype": "ColorFrameData"
              },
              {
                "Alpha": 255,
                "Color": {
                  "G": 0,
                  "B": 0
                },
                "FrameIndex": 165,
                "EasingData": {
                  "Type": 0
                },
                "ctype": "ColorFrameData"
              },
              {
                "Alpha": 255,
                "Color": {},
                "FrameIndex": 170,
                "EasingData": {
                  "Type": 0
                },
                "ctype": "ColorFrameData"
              }
            ],
            "ctype": "TimelineData"
          },
          {
            "ActionTag": 259146500,
            "Property": "Position",
            "Frames": [
              {
                "X": -1.3676,
                "Y": 318.2363,
                "FrameIndex": 0,
                "EasingData": {
                  "Type": 0
                },
                "ctype": "PointFrameData"
              },
              {
                "X": -1.3676,
                "Y": 331.2401,
                "FrameIndex": 60,
                "EasingData": {
                  "Type": 0
                },
                "ctype": "PointFrameData"
              },
              {
                "X": -1.3676,
                "Y": 318.2363,
                "FrameIndex": 120,
                "EasingData": {
                  "Type": 0
                },
                "ctype": "PointFrameData"
              },
              {
                "X": -1.3676,
                "Y": 318.2363,
                "FrameIndex": 121,
                "EasingData": {
                  "Type": 0
                },
                "ctype": "PointFrameData"
              },
              {
                "X": -1.3676,
                "Y": 332.24,
                "FrameIndex": 130,
                "EasingData": {
                  "Type": 0
                },
                "ctype": "PointFrameData"
              },
              {
                "X": -1.3676,
                "Y": 321.74,
                "FrameIndex": 135,
                "EasingData": {
                  "Type": 0
                },
                "ctype": "PointFrameData"
              },
              {
                "X": -1.3676,
                "Y": 318.2363,
                "FrameIndex": 150,
                "EasingData": {
                  "Type": 0
                },
                "ctype": "PointFrameData"
              },
              {
                "X": -1.3676,
                "Y": 318.2363,
                "FrameIndex": 151,
                "EasingData": {
                  "Type": 0
                },
                "ctype": "PointFrameData"
              },
              {
                "X": 8.6329,
                "Y": 318.2363,
                "FrameIndex": 155,
                "EasingData": {
                  "Type": 0
                },
                "ctype": "PointFrameData"
              },
              {
                "X": -13.3671,
                "Y": 318.2363,
                "FrameIndex": 160,
                "EasingData": {
                  "Type": 0
                },
                "ctype": "PointFrameData"
              },
              {
                "X": -1.3676,
                "Y": 308.2363,
                "FrameIndex": 165,
                "EasingData": {
                  "Type": 0
                },
                "ctype": "PointFrameData"
              },
              {
                "X": -1.3676,
                "Y": 318.2363,
                "FrameIndex": 170,
                "EasingData": {
                  "Type": 0
                },
                "ctype": "PointFrameData"
              },
              {
                "X": -1.3676,
                "Y": 318.2363,
                "FrameIndex": 171,
                "EasingData": {
                  "Type": 0
                },
                "ctype": "PointFrameData"
              },
              {
                "X": -1.3676,
                "Y": 318.2363,
                "FrameIndex": 190,
                "EasingData": {
                  "Type": 0
                },
                "ctype": "PointFrameData"
              },
              {
                "X": -1.3676,
                "Y": 318.2363,
                "FrameIndex": 260,
                "EasingData": {
                  "Type": 0
                },
                "ctype": "PointFrameData"
              }
            ],
            "ctype": "TimelineData"
          },
          {
            "ActionTag": 259146500,
            "Property": "Scale",
            "Frames": [
              {
                "X": 1.0,
                "Y": 1.0,
                "FrameIndex": 0,
                "EasingData": {
                  "Type": 0
                },
                "ctype": "ScaleValueFrameData"
              },
              {
                "X": 1.0,
                "Y": 1.02,
                "FrameIndex": 60,
                "EasingData": {
                  "Type": 0
                },
                "ctype": "ScaleValueFrameData"
              },
              {
                "X": 1.0,
                "Y": 1.0,
                "FrameIndex": 120,
                "EasingData": {
                  "Type": 0
                },
                "ctype": "ScaleValueFrameData"
              },
              {
                "X": 1.0,
                "Y": 1.0,
                "FrameIndex": 121,
                "EasingData": {
                  "Type": 0
                },
                "ctype": "ScaleValueFrameData"
              },
              {
                "X": 1.0,
                "Y": 1.02,
                "FrameIndex": 130,
                "EasingData": {
                  "Type": 0
                },
                "ctype": "ScaleValueFrameData"
              },
              {
                "X": 1.0,
                "Y": 0.995,
                "FrameIndex": 135,
                "EasingData": {
                  "Type": 0
                },
                "ctype": "ScaleValueFrameData"
              },
              {
                "X": 1.0,
                "Y": 1.0,
                "FrameIndex": 150,
                "EasingData": {
                  "Type": 0
                },
                "ctype": "ScaleValueFrameData"
              },
              {
                "X": 1.0,
                "Y": 1.0,
                "FrameIndex": 151,
                "EasingData": {
                  "Type": 0
                },
                "ctype": "ScaleValueFrameData"
              },
              {
                "X": 1.0,
                "Y": 1.0,
                "FrameIndex": 155,
                "EasingData": {
                  "Type": 0
                },
                "ctype": "ScaleValueFrameData"
              },
              {
                "X": 1.0,
                "Y": 1.0,
                "FrameIndex": 160,
                "EasingData": {
                  "Type": 0
                },
                "ctype": "ScaleValueFrameData"
              },
              {
                "X": 1.0,
                "Y": 1.0,
                "FrameIndex": 165,
                "EasingData": {
                  "Type": 0
                },
                "ctype": "ScaleValueFrameData"
              },
              {
                "X": 1.0,
                "Y": 1.0,
                "FrameIndex": 170,
                "EasingData": {
                  "Type": 0
                },
                "ctype": "ScaleValueFrameData"
              },
              {
                "X": 1.0,
                "Y": 1.0,
                "FrameIndex": 171,
                "EasingData": {
                  "Type": 0
                },
                "ctype": "ScaleValueFrameData"
              },
              {
                "X": 1.0,
                "Y": 1.0,
                "FrameIndex": 190,
                "EasingData": {
                  "Type": 0
                },
                "ctype": "ScaleValueFrameData"
              },
              {
                "X": 1.0,
                "Y": 1.0,
                "FrameIndex": 260,
                "EasingData": {
                  "Type": 0
                },
                "ctype": "ScaleValueFrameData"
              }
            ],
            "ctype": "TimelineData"
          },
          {
            "ActionTag": 259146500,
            "Property": "RotationSkew",
            "Frames": [
              {
                "X": 0.0,
                "Y": 0.0,
                "FrameIndex": 0,
                "EasingData": {
                  "Type": 0
                },
                "ctype": "ScaleValueFrameData"
              },
              {
                "X": 0.0,
                "Y": 0.0,
                "FrameIndex": 60,
                "EasingData": {
                  "Type": 0
                },
                "ctype": "ScaleValueFrameData"
              },
              {
                "X": 0.0,
                "Y": 0.0,
                "FrameIndex": 120,
                "EasingData": {
                  "Type": 0
                },
                "ctype": "ScaleValueFrameData"
              },
              {
                "X": 0.0,
                "Y": 0.0,
                "FrameIndex": 121,
                "EasingData": {
                  "Type": 0
                },
                "ctype": "ScaleValueFrameData"
              },
              {
                "X": 0.0,
                "Y": 0.0,
                "FrameIndex": 150,
                "EasingData": {
                  "Type": 0
                },
                "ctype": "ScaleValueFrameData"
              },
              {
                "X": 0.0,
                "Y": 0.0,
                "FrameIndex": 151,
                "EasingData": {
                  "Type": 0
                },
                "ctype": "ScaleValueFrameData"
              },
              {
                "X": 0.0,
                "Y": 0.0,
                "FrameIndex": 155,
                "EasingData": {
                  "Type": 0
                },
                "ctype": "ScaleValueFrameData"
              },
              {
                "X": 0.0,
                "Y": 0.0,
                "FrameIndex": 160,
                "EasingData": {
                  "Type": 0
                },
                "ctype": "ScaleValueFrameData"
              },
              {
                "X": 0.0,
                "Y": 0.0,
                "FrameIndex": 165,
                "EasingData": {
                  "Type": 0
                },
                "ctype": "ScaleValueFrameData"
              },
              {
                "X": 0.0,
                "Y": 0.0,
                "FrameIndex": 170,
                "EasingData": {
                  "Type": 0
                },
                "ctype": "ScaleValueFrameData"
              },
              {
                "X": 0.0,
                "Y": 0.0,
                "FrameIndex": 171,
                "EasingData": {
                  "Type": 0
                },
                "ctype": "ScaleValueFrameData"
              },
              {
                "X": 0.0,
                "Y": 0.0,
                "FrameIndex": 190,
                "EasingData": {
                  "Type": 0
                },
                "ctype": "ScaleValueFrameData"
              },
              {
                "X": 0.0,
                "Y": 0.0,
                "FrameIndex": 260,
                "EasingData": {
                  "Type": 0
                },
                "ctype": "ScaleValueFrameData"
              }
            ],
            "ctype": "TimelineData"
          },
          {
            "ActionTag": 259146500,
            "Property": "Alpha",
            "Frames": [
              {
                "Value": 255,
                "FrameIndex": 190,
                "EasingData": {
                  "Type": 0
                },
                "ctype": "IntFrameData"
              },
              {
                "Value": 0,
                "FrameIndex": 260,
                "EasingData": {
                  "Type": 0
                },
                "ctype": "IntFrameData"
              }
            ],
            "ctype": "TimelineData"
          },
          {
            "ActionTag": 259146500,
            "Property": "CColor",
            "Frames": [
              {
                "Alpha": 255,
                "Color": {},
                "FrameIndex": 151,
                "EasingData": {
                  "Type": 0
                },
                "ctype": "ColorFrameData"
              },
              {
                "Alpha": 255,
                "Color": {
                  "G": 0,
                  "B": 0
                },
                "FrameIndex": 155,
                "EasingData": {
                  "Type": 0
                },
                "ctype": "ColorFrameData"
              },
              {
                "Alpha": 255,
                "Color": {},
                "FrameIndex": 160,
                "EasingData": {
                  "Type": 0
                },
                "ctype": "ColorFrameData"
              },
              {
                "Alpha": 255,
                "Color": {
                  "G": 0,
                  "B": 0
                },
                "FrameIndex": 165,
                "EasingData": {
                  "Type": 0
                },
                "ctype": "ColorFrameData"
              },
              {
                "Alpha": 255,
                "Color": {},
                "FrameIndex": 170,
                "EasingData": {
                  "Type": 0
                },
                "ctype": "ColorFrameData"
              }
            ],
            "ctype": "TimelineData"
          },
          {
            "ActionTag": -2028005277,
            "Property": "Position",
            "Frames": [
              {
                "X": -17.5181,
                "Y": 310.46,
                "FrameIndex": 0,
                "EasingData": {
                  "Type": 0
                },
                "ctype": "PointFrameData"
              },
              {
                "X": -17.5181,
                "Y": 323.4601,
                "FrameIndex": 60,
                "EasingData": {
                  "Type": 0
                },
                "ctype": "PointFrameData"
              },
              {
                "X": -17.5181,
                "Y": 310.46,
                "FrameIndex": 120,
                "EasingData": {
                  "Type": 0
                },
                "ctype": "PointFrameData"
              },
              {
                "X": -17.5181,
                "Y": 310.46,
                "FrameIndex": 121,
                "EasingData": {
                  "Type": 0
                },
                "ctype": "PointFrameData"
              },
              {
                "X": -16.52,
                "Y": 319.46,
                "FrameIndex": 130,
                "EasingData": {
                  "Type": 0
                },
                "ctype": "PointFrameData"
              },
              {
                "X": -16.7695,
                "Y": 311.21,
                "FrameIndex": 135,
                "EasingData": {
                  "Type": 0
                },
                "ctype": "PointFrameData"
              },
              {
                "X": -17.0193,
                "Y": 310.9601,
                "FrameIndex": 140,
                "EasingData": {
                  "Type": 0
                },
                "ctype": "PointFrameData"
              },
              {
                "X": -17.5181,
                "Y": 310.46,
                "FrameIndex": 150,
                "EasingData": {
                  "Type": 0
                },
                "ctype": "PointFrameData"
              },
              {
                "X": -17.5181,
                "Y": 310.46,
                "FrameIndex": 151,
                "EasingData": {
                  "Type": 0
                },
                "ctype": "PointFrameData"
              },
              {
                "X": -7.5179,
                "Y": 310.46,
                "FrameIndex": 155,
                "EasingData": {
                  "Type": 0
                },
                "ctype": "PointFrameData"
              },
              {
                "X": -29.5179,
                "Y": 310.46,
                "FrameIndex": 160,
                "EasingData": {
                  "Type": 0
                },
                "ctype": "PointFrameData"
              },
              {
                "X": -17.5181,
                "Y": 300.4598,
                "FrameIndex": 165,
                "EasingData": {
                  "Type": 0
                },
                "ctype": "PointFrameData"
              },
              {
                "X": -17.5181,
                "Y": 310.46,
                "FrameIndex": 170,
                "EasingData": {
                  "Type": 0
                },
                "ctype": "PointFrameData"
              },
              {
                "X": -17.5181,
                "Y": 310.46,
                "FrameIndex": 171,
                "EasingData": {
                  "Type": 0
                },
                "ctype": "PointFrameData"
              },
              {
                "X": -17.5181,
                "Y": 310.46,
                "FrameIndex": 190,
                "EasingData": {
                  "Type": 0
                },
                "ctype": "PointFrameData"
              },
              {
                "X": -17.5181,
                "Y": 310.46,
                "FrameIndex": 260,
                "EasingData": {
                  "Type": 0
                },
                "ctype": "PointFrameData"
              }
            ],
            "ctype": "TimelineData"
          },
          {
            "ActionTag": -2028005277,
            "Property": "Scale",
            "Frames": [
              {
                "X": 1.0,
                "Y": 1.0,
                "FrameIndex": 0,
                "EasingData": {
                  "Type": 0
                },
                "ctype": "ScaleValueFrameData"
              },
              {
                "X": 1.0,
                "Y": 1.02,
                "FrameIndex": 60,
                "EasingData": {
                  "Type": 0
                },
                "ctype": "ScaleValueFrameData"
              },
              {
                "X": 1.0,
                "Y": 1.0,
                "FrameIndex": 120,
                "EasingData": {
                  "Type": 0
                },
                "ctype": "ScaleValueFrameData"
              },
              {
                "X": 1.0,
                "Y": 1.0,
                "FrameIndex": 121,
                "EasingData": {
                  "Type": 0
                },
                "ctype": "ScaleValueFrameData"
              },
              {
                "X": 1.0,
                "Y": 1.02,
                "FrameIndex": 130,
                "EasingData": {
                  "Type": 0
                },
                "ctype": "ScaleValueFrameData"
              },
              {
                "X": 1.0,
                "Y": 0.995,
                "FrameIndex": 135,
                "EasingData": {
                  "Type": 0
                },
                "ctype": "ScaleValueFrameData"
              },
              {
                "X": 1.0,
                "Y": 1.0,
                "FrameIndex": 150,
                "EasingData": {
                  "Type": 0
                },
                "ctype": "ScaleValueFrameData"
              },
              {
                "X": 1.0,
                "Y": 1.0,
                "FrameIndex": 151,
                "EasingData": {
                  "Type": 0
                },
                "ctype": "ScaleValueFrameData"
              },
              {
                "X": 1.0,
                "Y": 1.0,
                "FrameIndex": 155,
                "EasingData": {
                  "Type": 0
                },
                "ctype": "ScaleValueFrameData"
              },
              {
                "X": 1.0,
                "Y": 1.0,
                "FrameIndex": 160,
                "EasingData": {
                  "Type": 0
                },
                "ctype": "ScaleValueFrameData"
              },
              {
                "X": 1.0,
                "Y": 1.0,
                "FrameIndex": 165,
                "EasingData": {
                  "Type": 0
                },
                "ctype": "ScaleValueFrameData"
              },
              {
                "X": 1.0,
                "Y": 1.0,
                "FrameIndex": 170,
                "EasingData": {
                  "Type": 0
                },
                "ctype": "ScaleValueFrameData"
              },
              {
                "X": 1.0,
                "Y": 1.0,
                "FrameIndex": 171,
                "EasingData": {
                  "Type": 0
                },
                "ctype": "ScaleValueFrameData"
              },
              {
                "X": 1.0,
                "Y": 1.0,
                "FrameIndex": 190,
                "EasingData": {
                  "Type": 0
                },
                "ctype": "ScaleValueFrameData"
              },
              {
                "X": 1.0,
                "Y": 1.0,
                "FrameIndex": 260,
                "EasingData": {
                  "Type": 0
                },
                "ctype": "ScaleValueFrameData"
              }
            ],
            "ctype": "TimelineData"
          },
          {
            "ActionTag": -2028005277,
            "Property": "RotationSkew",
            "Frames": [
              {
                "X": 0.0,
                "Y": 0.0,
                "FrameIndex": 0,
                "EasingData": {
                  "Type": 0
                },
                "ctype": "ScaleValueFrameData"
              },
              {
                "X": 0.0,
                "Y": 0.0,
                "FrameIndex": 60,
                "EasingData": {
                  "Type": 0
                },
                "ctype": "ScaleValueFrameData"
              },
              {
                "X": 0.0,
                "Y": 0.0,
                "FrameIndex": 120,
                "EasingData": {
                  "Type": 0
                },
                "ctype": "ScaleValueFrameData"
              },
              {
                "X": 0.0,
                "Y": 0.0,
                "FrameIndex": 121,
                "EasingData": {
                  "Type": 0
                },
                "ctype": "ScaleValueFrameData"
              },
              {
                "X": 16.0,
                "Y": 16.0,
                "FrameIndex": 130,
                "EasingData": {
                  "Type": 0
                },
                "ctype": "ScaleValueFrameData"
              },
              {
                "X": -7.0,
                "Y": -7.0,
                "FrameIndex": 135,
                "EasingData": {
                  "Type": 0
                },
                "ctype": "ScaleValueFrameData"
              },
              {
                "X": 5.8241,
                "Y": 5.8221,
                "FrameIndex": 140,
                "EasingData": {
                  "Type": 0
                },
                "ctype": "ScaleValueFrameData"
              },
              {
                "X": 0.0,
                "Y": 0.0,
                "FrameIndex": 150,
                "EasingData": {
                  "Type": 0
                },
                "ctype": "ScaleValueFrameData"
              },
              {
                "X": 0.0,
                "Y": 0.0,
                "FrameIndex": 151,
                "EasingData": {
                  "Type": 0
                },
                "ctype": "ScaleValueFrameData"
              },
              {
                "X": 0.0,
                "Y": 0.0,
                "FrameIndex": 155,
                "EasingData": {
                  "Type": 0
                },
                "ctype": "ScaleValueFrameData"
              },
              {
                "X": 0.0,
                "Y": 0.0,
                "FrameIndex": 160,
                "EasingData": {
                  "Type": 0
                },
                "ctype": "ScaleValueFrameData"
              },
              {
                "X": 0.0,
                "Y": 0.0,
                "FrameIndex": 165,
                "EasingData": {
                  "Type": 0
                },
                "ctype": "ScaleValueFrameData"
              },
              {
                "X": 0.0,
                "Y": 0.0,
                "FrameIndex": 170,
                "EasingData": {
                  "Type": 0
                },
                "ctype": "ScaleValueFrameData"
              },
              {
                "X": 0.0,
                "Y": 0.0,
                "FrameIndex": 171,
                "EasingData": {
                  "Type": 0
                },
                "ctype": "ScaleValueFrameData"
              },
              {
                "X": 0.0,
                "Y": 0.0,
                "FrameIndex": 190,
                "EasingData": {
                  "Type": 0
                },
                "ctype": "ScaleValueFrameData"
              },
              {
                "X": 0.0,
                "Y": 0.0,
                "FrameIndex": 260,
                "EasingData": {
                  "Type": 0
                },
                "ctype": "ScaleValueFrameData"
              }
            ],
            "ctype": "TimelineData"
          },
          {
            "ActionTag": -2028005277,
            "Property": "Alpha",
            "Frames": [
              {
                "Value": 255,
                "FrameIndex": 190,
                "EasingData": {
                  "Type": 0
                },
                "ctype": "IntFrameData"
              },
              {
                "Value": 0,
                "FrameIndex": 260,
                "EasingData": {
                  "Type": 0
                },
                "ctype": "IntFrameData"
              }
            ],
            "ctype": "TimelineData"
          },
          {
            "ActionTag": -2028005277,
            "Property": "CColor",
            "Frames": [
              {
                "Alpha": 255,
                "Color": {},
                "FrameIndex": 151,
                "EasingData": {
                  "Type": 0
                },
                "ctype": "ColorFrameData"
              },
              {
                "Alpha": 255,
                "Color": {
                  "G": 0,
                  "B": 0
                },
                "FrameIndex": 155,
                "EasingData": {
                  "Type": 0
                },
                "ctype": "ColorFrameData"
              },
              {
                "Alpha": 255,
                "Color": {},
                "FrameIndex": 160,
                "EasingData": {
                  "Type": 0
                },
                "ctype": "ColorFrameData"
              },
              {
                "Alpha": 255,
                "Color": {
                  "G": 0,
                  "B": 0
                },
                "FrameIndex": 165,
                "EasingData": {
                  "Type": 0
                },
                "ctype": "ColorFrameData"
              },
              {
                "Alpha": 255,
                "Color": {},
                "FrameIndex": 170,
                "EasingData": {
                  "Type": 0
                },
                "ctype": "ColorFrameData"
              }
            ],
            "ctype": "TimelineData"
          },
          {
            "ActionTag": -582630817,
            "Property": "Position",
            "Frames": [
              {
                "X": 29.8572,
                "Y": 32.6394,
                "FrameIndex": 121,
                "EasingData": {
                  "Type": 0
                },
                "ctype": "PointFrameData"
              },
              {
                "X": 111.0195,
                "Y": 208.3088,
                "FrameIndex": 130,
                "EasingData": {
                  "Type": 0
                },
                "ctype": "PointFrameData"
              },
              {
                "X": -138.2305,
                "Y": 234.1448,
                "FrameIndex": 135,
                "EasingData": {
                  "Type": 0
                },
                "ctype": "PointFrameData"
              },
              {
                "X": -110.0302,
                "Y": 387.5369,
                "FrameIndex": 140,
                "EasingData": {
                  "Type": 0
                },
                "ctype": "PointFrameData"
              },
              {
                "X": 38.8525,
                "Y": 415.7322,
                "FrameIndex": 150,
                "EasingData": {
                  "Type": 0
                },
                "ctype": "PointFrameData"
              }
            ],
            "ctype": "TimelineData"
          },
          {
            "ActionTag": -582630817,
            "Property": "Scale",
            "Frames": [
              {
                "X": 1.0,
                "Y": 1.0,
                "FrameIndex": 121,
                "EasingData": {
                  "Type": 0
                },
                "ctype": "ScaleValueFrameData"
              },
              {
                "X": 1.0,
                "Y": 1.0,
                "FrameIndex": 130,
                "EasingData": {
                  "Type": 0
                },
                "ctype": "ScaleValueFrameData"
              },
              {
                "X": 1.0,
                "Y": 1.0,
                "FrameIndex": 135,
                "EasingData": {
                  "Type": 0
                },
                "ctype": "ScaleValueFrameData"
              },
              {
                "X": 0.8961,
                "Y": 1.0,
                "FrameIndex": 140,
                "EasingData": {
                  "Type": 0
                },
                "ctype": "ScaleValueFrameData"
              },
              {
                "X": 0.7547,
                "Y": 1.0,
                "FrameIndex": 150,
                "EasingData": {
                  "Type": 0
                },
                "ctype": "ScaleValueFrameData"
              }
            ],
            "ctype": "TimelineData"
          },
          {
            "ActionTag": -582630817,
            "Property": "RotationSkew",
            "Frames": [
              {
                "X": 150.8152,
                "Y": 150.8156,
                "FrameIndex": 121,
                "EasingData": {
                  "Type": 0
                },
                "ctype": "ScaleValueFrameData"
              },
              {
                "X": 121.7171,
                "Y": 121.7114,
                "FrameIndex": 130,
                "EasingData": {
                  "Type": 0
                },
                "ctype": "ScaleValueFrameData"
              },
              {
                "X": 247.9983,
                "Y": 248.0002,
                "FrameIndex": 135,
                "EasingData": {
                  "Type": 0
                },
                "ctype": "ScaleValueFrameData"
              },
              {
                "X": 310.3411,
                "Y": 310.3384,
                "FrameIndex": 140,
                "EasingData": {
                  "Type": 0
                },
                "ctype": "ScaleValueFrameData"
              },
              {
                "X": 397.0977,
                "Y": 397.0959,
                "FrameIndex": 150,
                "EasingData": {
                  "Type": 0
                },
                "ctype": "ScaleValueFrameData"
              }
            ],
            "ctype": "TimelineData"
          },
          {
            "ActionTag": -582630817,
            "Property": "Alpha",
            "Frames": [
              {
                "Value": 0,
                "FrameIndex": 121,
                "EasingData": {
                  "Type": 0
                },
                "ctype": "IntFrameData"
              },
              {
                "Value": 0,
                "FrameIndex": 130,
                "EasingData": {
                  "Type": 0
                },
                "ctype": "IntFrameData"
              },
              {
                "Value": 255,
                "FrameIndex": 135,
                "EasingData": {
                  "Type": 0
                },
                "ctype": "IntFrameData"
              },
              {
                "Value": 0,
                "FrameIndex": 150,
                "EasingData": {
                  "Type": 0
                },
                "ctype": "IntFrameData"
              }
            ],
            "ctype": "TimelineData"
          },
          {
            "ActionTag": -582630817,
            "Property": "CColor",
            "Frames": [
              {
                "Alpha": 255,
                "Color": {
                  "R": 30,
                  "G": 144
                },
                "FrameIndex": 121,
                "EasingData": {
                  "Type": 0
                },
                "ctype": "ColorFrameData"
              }
            ],
            "ctype": "TimelineData"
          },
          {
            "ActionTag": -582630817,
            "Property": "BlendFunc",
            "Frames": [
              {
                "Src": 1,
                "Dst": 1,
                "FrameIndex": 121,
                "Tween": false,
                "ctype": "BlendFuncFrameData"
              }
            ],
            "ctype": "TimelineData"
          },
          {
            "ActionTag": 182928575,
            "Property": "Position",
            "Frames": [
              {
                "X": 29.8572,
                "Y": 32.6394,
                "FrameIndex": 121,
                "EasingData": {
                  "Type": 0
                },
                "ctype": "PointFrameData"
              },
              {
                "X": 153.5529,
                "Y": 279.758,
                "FrameIndex": 130,
                "EasingData": {
                  "Type": 0
                },
                "ctype": "PointFrameData"
              },
              {
                "X": -109.3094,
                "Y": 212.8798,
                "FrameIndex": 135,
                "EasingData": {
                  "Type": 0
                },
                "ctype": "PointFrameData"
              },
              {
                "X": -110.0265,
                "Y": 387.5364,
                "FrameIndex": 140,
                "EasingData": {
                  "Type": 0
                },
                "ctype": "PointFrameData"
              },
              {
                "X": 43.1062,
                "Y": 423.388,
                "FrameIndex": 150,
                "EasingData": {
                  "Type": 0
                },
                "ctype": "PointFrameData"
              }
            ],
            "ctype": "TimelineData"
          },
          {
            "ActionTag": 182928575,
            "Property": "Scale",
            "Frames": [
              {
                "X": 1.0,
                "Y": 1.0,
                "FrameIndex": 121,
                "EasingData": {
                  "Type": 0
                },
                "ctype": "ScaleValueFrameData"
              },
              {
                "X": 1.0,
                "Y": 1.1992,
                "FrameIndex": 130,
                "EasingData": {
                  "Type": 0
                },
                "ctype": "ScaleValueFrameData"
              },
              {
                "X": 1.0,
                "Y": 1.5295,
                "FrameIndex": 135,
                "EasingData": {
                  "Type": 0
                },
                "ctype": "ScaleValueFrameData"
              },
              {
                "X": 1.2652,
                "Y": 1.4643,
                "FrameIndex": 140,
                "EasingData": {
                  "Type": 0
                },
                "ctype": "ScaleValueFrameData"
              },
              {
                "X": 0.9599,
                "Y": 1.0,
                "FrameIndex": 150,
                "EasingData": {
                  "Type": 0
                },
                "ctype": "ScaleValueFrameData"
              }
            ],
            "ctype": "TimelineData"
          },
          {
            "ActionTag": 182928575,
            "Property": "RotationSkew",
            "Frames": [
              {
                "X": 150.8152,
                "Y": 150.8156,
                "FrameIndex": 121,
                "EasingData": {
                  "Type": 0
                },
                "ctype": "ScaleValueFrameData"
              },
              {
                "X": 100.107,
                "Y": 100.1002,
                "FrameIndex": 130,
                "EasingData": {
                  "Type": 0
                },
                "ctype": "ScaleValueFrameData"
              },
              {
                "X": 229.6623,
                "Y": 229.6629,
                "FrameIndex": 135,
                "EasingData": {
                  "Type": 0
                },
                "ctype": "ScaleValueFrameData"
              },
              {
                "X": 326.1622,
                "Y": 326.158,
                "FrameIndex": 140,
                "EasingData": {
                  "Type": 0
                },
                "ctype": "ScaleValueFrameData"
              },
              {
                "X": 408.3568,
                "Y": 408.3555,
                "FrameIndex": 150,
                "EasingData": {
                  "Type": 0
                },
                "ctype": "ScaleValueFrameData"
              }
            ],
            "ctype": "TimelineData"
          },
          {
            "ActionTag": 182928575,
            "Property": "Alpha",
            "Frames": [
              {
                "Value": 0,
                "FrameIndex": 121,
                "EasingData": {
                  "Type": 0
                },
                "ctype": "IntFrameData"
              },
              {
                "Value": 0,
                "FrameIndex": 130,
                "EasingData": {
                  "Type": 0
                },
                "ctype": "IntFrameData"
              },
              {
                "Value": 255,
                "FrameIndex": 135,
                "EasingData": {
                  "Type": 0
                },
                "ctype": "IntFrameData"
              },
              {
                "Value": 0,
                "FrameIndex": 150,
                "EasingData": {
                  "Type": 0
                },
                "ctype": "IntFrameData"
              }
            ],
            "ctype": "TimelineData"
          },
          {
            "ActionTag": 182928575,
            "Property": "CColor",
            "Frames": [
              {
                "Alpha": 255,
                "Color": {
                  "R": 30,
                  "G": 144
                },
                "FrameIndex": 121,
                "EasingData": {
                  "Type": 0
                },
                "ctype": "ColorFrameData"
              }
            ],
            "ctype": "TimelineData"
          },
          {
            "ActionTag": 182928575,
            "Property": "BlendFunc",
            "Frames": [
              {
                "Src": 1,
                "Dst": 1,
                "FrameIndex": 121,
                "Tween": false,
                "ctype": "BlendFuncFrameData"
              }
            ],
            "ctype": "TimelineData"
          }
        ],
        "ctype": "TimelineActionData"
      },
      "AnimationList": [
        {
          "StartIndex": 0,
          "EndIndex": 120,
          "Name": "standby",
          "ctype": "AnimationInfoData"
        },
        {
          "StartIndex": 121,
          "EndIndex": 150,
          "Name": "attack",
          "ctype": "AnimationInfoData"
        },
        {
          "StartIndex": 151,
          "EndIndex": 170,
          "Name": "hurt",
          "ctype": "AnimationInfoData"
        },
        {
          "StartIndex": 171,
          "EndIndex": 260,
          "Name": "dead",
          "ctype": "AnimationInfoData"
        }
      ],
      "ObjectData": {
        "Tag": 3025,
        "Children": [
          {
            "BackColorAlpha": 102,
            "ComboBoxIndex": 1,
            "SingleColor": {
              "R": 150,
              "G": 200
            },
            "FirstColor": {
              "R": 150,
              "G": 200
            },
            "EndColor": {},
            "ColorVector": {
              "ScaleY": 1.0
            },
            "Scale9Width": 1,
            "Scale9Height": 1,
            "TouchEnable": true,
            "AnchorPoint": {
              "ScaleX": 0.5
            },
            "Position": {
              "X": 0.0,
              "Y": 310.0
            },
            "Scale": {
              "ScaleX": 1.0,
              "ScaleY": 1.0
            },
            "CColor": {},
            "IconVisible": false,
            "PrePosition": {
              "X": 0.0,
              "Y": 0.0
            },
            "PreSize": {
              "X": 0.0,
              "Y": 0.0
            },
            "LeftMargin": -0.5,
            "RightMargin": -0.5,
            "TopMargin": -311.0,
            "BottomMargin": 310.0,
            "Tag": 318,
            "ActionTag": -1501241929,
            "Size": {
              "X": 1.0,
              "Y": 1.0
            },
            "Name": "attack",
            "ctype": "PanelObjectData"
          },
          {
            "BackColorAlpha": 102,
            "ComboBoxIndex": 1,
            "SingleColor": {
              "R": 150,
              "G": 200
            },
            "FirstColor": {
              "R": 150,
              "G": 200
            },
            "EndColor": {},
            "ColorVector": {
              "ScaleY": 1.0
            },
            "Scale9Width": 1,
            "Scale9Height": 1,
            "TouchEnable": true,
            "AnchorPoint": {
              "ScaleX": 0.5
            },
            "Position": {
              "X": 0.0,
              "Y": 330.0
            },
            "Scale": {
              "ScaleX": 1.0,
              "ScaleY": 1.0
            },
            "CColor": {},
            "IconVisible": false,
            "PrePosition": {
              "X": 0.0,
              "Y": 0.0
            },
            "PreSize": {
              "X": 0.0,
              "Y": 0.0
            },
            "LeftMargin": -0.5,
            "RightMargin": -0.5,
            "TopMargin": -331.0,
            "BottomMargin": 330.0,
            "Tag": 655,
            "ActionTag": -95953394,
            "Size": {
              "X": 1.0,
              "Y": 1.0
            },
            "Name": "pos",
            "ctype": "PanelObjectData"
          },
          {
            "FileData": {
              "Type": "Normal",
              "Path": "animation/res/monster/shadow.png",
              "Plist": ""
            },
            "BlendFunc": {
              "Src": 770,
              "Dst": 771
            },
            "AnchorPoint": {
              "ScaleX": 0.5,
              "ScaleY": 0.5
            },
            "Position": {
              "X": 0.0,
              "Y": 0.0
            },
            "Scale": {
              "ScaleX": 1.0,
              "ScaleY": 1.0
            },
            "CColor": {},
            "IconVisible": false,
            "PositionPercentXEnabled": true,
            "PositionPercentYEnabled": true,
            "PrePosition": {
              "X": 0.0,
              "Y": 0.0
            },
            "PreSize": {
              "X": 0.0,
              "Y": 0.0
            },
            "LeftMargin": -117.0,
            "RightMargin": -117.0,
            "TopMargin": -37.5,
            "BottomMargin": -37.5,
            "Tag": 649,
            "ActionTag": 1459686813,
            "Size": {
              "X": 234.0,
              "Y": 75.0
            },
            "Name": "shadow",
            "ctype": "SpriteObjectData"
          },
          {
            "FileData": {
              "Type": "MarkedSubImage",
              "Path": "animation/res/monster/new/newFennuyouhun/r.png",
              "Plist": "animation/res/monster/mon42.plist"
            },
            "BlendFunc": {
              "Src": 770,
              "Dst": 771
            },
            "AnchorPoint": {
              "ScaleX": 0.5503,
              "ScaleY": 0.834
            },
            "Position": {
              "X": 20.2947,
              "Y": 316.7978
            },
            "Scale": {
              "ScaleX": 1.0,
              "ScaleY": 1.0
            },
            "CColor": {},
            "IconVisible": false,
            "PrePosition": {
              "X": 0.0,
              "Y": 0.0
            },
            "PreSize": {
              "X": 0.0,
              "Y": 0.0
            },
            "LeftMargin": -124.4342,
            "RightMargin": -138.5658,
            "TopMargin": -366.4318,
            "BottomMargin": 67.4318,
            "Tag": 645,
            "ActionTag": -46686393,
            "Size": {
              "X": 263.0,
              "Y": 299.0
            },
            "Name": "r_5",
            "ctype": "SpriteObjectData"
          },
          {
            "FileData": {
              "Type": "MarkedSubImage",
              "Path": "animation/res/monster/new/newFennuyouhun/body.png",
              "Plist": "animation/res/monster/mon42.plist"
            },
            "BlendFunc": {
              "Src": 770,
              "Dst": 771
            },
            "AnchorPoint": {
              "ScaleX": 0.6403
            },
            "Position": {
              "X": 8.8333,
              "Y": 217.5331
            },
            "Scale": {
              "ScaleX": 1.0,
              "ScaleY": 1.0
            },
            "CColor": {},
            "IconVisible": false,
            "PrePosition": {
              "X": 0.0,
              "Y": 0.0
            },
            "PreSize": {
              "X": 0.0,
              "Y": 0.0
            },
            "LeftMargin": -50.7146,
            "RightMargin": -42.2854,
            "TopMargin": -330.5331,
            "BottomMargin": 217.5331,
            "Tag": 642,
            "ActionTag": -1583887602,
            "Size": {
              "X": 93.0,
              "Y": 113.0
            },
            "Name": "body_2",
            "ctype": "SpriteObjectData"
          },
          {
            "FileData": {
              "Type": "MarkedSubImage",
              "Path": "animation/res/monster/new/newFennuyouhun/leg.png",
              "Plist": "animation/res/monster/mon42.plist"
            },
            "BlendFunc": {
              "Src": 770,
              "Dst": 771
            },
            "AnchorPoint": {
              "ScaleX": 0.5
            },
            "Position": {
              "X": 2.8178,
              "Y": 33.3434
            },
            "Scale": {
              "ScaleX": 1.0,
              "ScaleY": 1.0
            },
            "CColor": {},
            "IconVisible": false,
            "PrePosition": {
              "X": 0.0,
              "Y": 0.0
            },
            "PreSize": {
              "X": 0.0,
              "Y": 0.0
            },
            "LeftMargin": -35.1822,
            "RightMargin": -40.8178,
            "TopMargin": -245.3434,
            "BottomMargin": 33.3434,
            "Tag": 641,
            "ActionTag": -2026200248,
            "Size": {
              "X": 76.0,
              "Y": 212.0
            },
            "Name": "leg_1",
            "ctype": "SpriteObjectData"
          },
          {
            "FileData": {
              "Type": "MarkedSubImage",
              "Path": "animation/res/monster/new/newFennuyouhun/head.png",
              "Plist": "animation/res/monster/mon42.plist"
            },
            "BlendFunc": {
              "Src": 770,
              "Dst": 771
            },
            "AnchorPoint": {
              "ScaleX": 0.5
            },
            "Position": {
              "X": -1.3676,
              "Y": 318.2363
            },
            "Scale": {
              "ScaleX": 1.0,
              "ScaleY": 1.0
            },
            "CColor": {},
            "IconVisible": false,
            "PrePosition": {
              "X": 0.0,
              "Y": 0.0
            },
            "PreSize": {
              "X": 0.0,
              "Y": 0.0
            },
            "LeftMargin": -24.8676,
            "RightMargin": -22.1324,
            "TopMargin": -406.2363,
            "BottomMargin": 318.2363,
            "Tag": 643,
            "ActionTag": 259146500,
            "Size": {
              "X": 47.0,
              "Y": 88.0
            },
            "Name": "head_3",
            "ctype": "SpriteObjectData"
          },
          {
            "FileData": {
              "Type": "MarkedSubImage",
              "Path": "animation/res/monster/new/newFennuyouhun/l.png",
              "Plist": "animation/res/monster/mon42.plist"
            },
            "BlendFunc": {
              "Src": 770,
              "Dst": 771
            },
            "AnchorPoint": {
              "ScaleX": 1.0,
              "ScaleY": 0.7271
            },
            "Position": {
              "X": -17.5181,
              "Y": 310.46
            },
            "Scale": {
              "ScaleX": 1.0,
              "ScaleY": 1.0
            },
            "CColor": {},
            "IconVisible": false,
            "PrePosition": {
              "X": 0.0,
              "Y": 0.0
            },
            "PreSize": {
              "X": 0.0,
              "Y": 0.0
            },
            "LeftMargin": -104.5181,
            "RightMargin": 17.5181,
            "TopMargin": -363.1297,
            "BottomMargin": 170.1297,
            "Tag": 644,
            "ActionTag": -2028005277,
            "Size": {
              "X": 87.0,
              "Y": 193.0
            },
            "Name": "l_4",
            "ctype": "SpriteObjectData"
          },
          {
            "FlipX": true,
            "FileData": {
              "Type": "MarkedSubImage",
              "Path": "animation/res/attack/ef_axe/fx_glo02123.png",
              "Plist": "animation/res/ef1.plist"
            },
            "BlendFunc": {
              "Src": 1,
              "Dst": 1
            },
            "AnchorPoint": {
              "ScaleX": 0.5,
              "ScaleY": 0.5
            },
            "Position": {
              "X": 29.8572,
              "Y": 32.6394
            },
            "Scale": {
              "ScaleX": 1.0,
              "ScaleY": 1.0
            },
            "RotationSkewX": 150.8152,
            "RotationSkewY": 150.8156,
            "CColor": {
              "R": 30,
              "G": 144
            },
            "IconVisible": false,
            "PrePosition": {
              "X": 0.0,
              "Y": 0.0
            },
            "PreSize": {
              "X": 0.0,
              "Y": 0.0
            },
            "LeftMargin": -167.6428,
            "RightMargin": -227.3572,
            "TopMargin": -129.6394,
            "BottomMargin": -64.3606,
            "Tag": 1063,
            "ActionTag": -582630817,
            "Size": {
              "X": 395.0,
              "Y": 194.0
            },
            "Alpha": 0,
            "Name": "fx_glo02123_7",
            "ctype": "SpriteObjectData"
          },
          {
            "FlipX": true,
            "FileData": {
              "Type": "MarkedSubImage",
              "Path": "animation/res/attack/ef_axe/fx_glo02123.png",
              "Plist": "animation/res/ef1.plist"
            },
            "BlendFunc": {
              "Src": 1,
              "Dst": 1
            },
            "AnchorPoint": {
              "ScaleX": 0.5,
              "ScaleY": 0.5
            },
            "Position": {
              "X": 29.8572,
              "Y": 32.6394
            },
            "Scale": {
              "ScaleX": 1.0,
              "ScaleY": 1.0
            },
            "RotationSkewX": 150.8152,
            "RotationSkewY": 150.8156,
            "CColor": {
              "R": 30,
              "G": 144
            },
            "IconVisible": false,
            "PrePosition": {
              "X": 0.0,
              "Y": 0.0
            },
            "PreSize": {
              "X": 0.0,
              "Y": 0.0
            },
            "LeftMargin": -167.6428,
            "RightMargin": -227.3572,
            "TopMargin": -129.6394,
            "BottomMargin": -64.3606,
            "Tag": 33,
            "ActionTag": 182928575,
            "Size": {
              "X": 395.0,
              "Y": 194.0
            },
            "Alpha": 0,
            "Name": "fx_glo02123_7_0",
            "ctype": "SpriteObjectData"
          }
        ],
        "Size": {
          "X": 0.0,
          "Y": 0.0
        },
        "Name": "Node",
        "ctype": "SingleNodeObjectData"
      },
      "UsedResources": [
        "../res/ef1.plist",
        "../res/ef1.png",
        "../res/monster/mon42.plist",
        "../res/monster/mon42.png",
        "../res/monster/shadow.png"
      ],
      "ctype": "GameFileData"
    }
  },
  "Type": "Node"
}